brainstem/Entity_Entity.py
brainstem/__init__.py
brainstem/_bs_c_cffi.py
brainstem/_factory.py
brainstem/_factory_uei.py
brainstem/autoGen_Analog_Entity.py
brainstem/autoGen_App_Entity.py
brainstem/autoGen_Clock_Entity.py
brainstem/autoGen_Digital_Entity.py
brainstem/autoGen_Entity.py
brainstem/autoGen_Equalizer_Entity.py
brainstem/autoGen_Ethernet_Entity.py
brainstem/autoGen_HDBaseT_Entity.py
brainstem/autoGen_I2C_Entity.py
brainstem/autoGen_Mux_Entity.py
brainstem/autoGen_PoE_Entity.py
brainstem/autoGen_Pointer_Entity.py
brainstem/autoGen_Port_Entity.py
brainstem/autoGen_PowerDelivery_Entity.py
brainstem/autoGen_RCServo_Entity.py
brainstem/autoGen_Rail_Entity.py
brainstem/autoGen_Relay_Entity.py
brainstem/autoGen_Signal_Entity.py
brainstem/autoGen_Store_Entity.py
brainstem/autoGen_System_Entity.py
brainstem/autoGen_Temperature_Entity.py
brainstem/autoGen_Timer_Entity.py
brainstem/autoGen_UART_Entity.py
brainstem/autoGen_USBSystem_Entity.py
brainstem/autoGen_USB_Entity.py
brainstem/defs.py
brainstem/discover.py
brainstem/entity.py
brainstem/ffi_utils.py
brainstem/libBrainStem2-CCA.dylib
brainstem/link.py
brainstem/module.py
brainstem/pd_channel_logger.py
brainstem/result.py
brainstem/stem.py
brainstem/version.py
brainstem/Linux/aarch64/Ubuntu/16.04/libBrainStem2.so
brainstem/Linux/aarch64/Ubuntu/16.04/libBrainStem2_CCA.so
brainstem/Linux/aarch64/Ubuntu/18.04/libBrainStem2.so
brainstem/Linux/aarch64/Ubuntu/18.04/libBrainStem2_CCA.so
brainstem/Linux/aarch64/Ubuntu/20.04/libBrainStem2.so
brainstem/Linux/aarch64/Ubuntu/20.04/libBrainStem2_CCA.so
brainstem/Linux/aarch64/Ubuntu/22.04/libBrainStem2.so
brainstem/Linux/aarch64/Ubuntu/22.04/libBrainStem2_CCA.so
brainstem/Linux/armv7l/debian/11.7/libBrainStem2.so
brainstem/Linux/armv7l/debian/11.7/libBrainStem2_CCA.so
brainstem/Linux/i686/Ubuntu/16.04/libBrainStem2.so
brainstem/Linux/i686/Ubuntu/16.04/libBrainStem2_CCA.so
brainstem/Linux/x86_64/Ubuntu/16.04/libBrainStem2.so
brainstem-2.12.0.dist-info/LICENSE
brainstem-2.12.0.dist-info/METADATA
brainstem-2.12.0.dist-info/WHEEL
brainstem-2.12.0.dist-info/top_level.txt
brainstem-2.12.0.dist-info/RECORD
