Metadata-Version: 2.1
Name: brainstem
Version: 2.12.0
Summary: Acroname BrainStem Software Control Package
Home-page: http://www.acroname.com
Author: Acroname Inc.
Author-email: support@acroname.com
License: # Brainstem SDK Software Package License Agreement:
Classifier: Programming Language :: Python :: 2
Classifier: Programming Language :: Python :: 3
Classifier: License :: Other/Proprietary License
Classifier: Operating System :: OS Independent
License-File: LICENSE
Requires-Dist: cffi (<2.0.0,>=1.0.0) ; python_version <= "3.8"
Requires-Dist: cffi (>=1.0.0) ; python_version > "3.8"
